sklearn_esa/__init__.py
sklearn_esa/esa/__init__.py
sklearn_esa/esa/esa.py
sklearn_esa/tf_idf/__init__.py
sklearn_esa/tf_idf/tf_idf.py
sklearn_esa-0.0.13.dist-info/LICENSE
sklearn_esa-0.0.13.dist-info/METADATA
sklearn_esa-0.0.13.dist-info/WHEEL
sklearn_esa-0.0.13.dist-info/top_level.txt
sklearn_esa-0.0.13.dist-info/RECORD
